{"name":"Tiffany (Yu Jou) Tang","otherName":"Gnat","years":1,"location":"Taipei/London","website":null,"youtube":null,"vimeo":null,"twitch":null,"facebook":null,"twitter":null,"instagram":"gnat_poisson","publicEmail":"tiffanytang0128@gmail.com","slug":"tiffany-yu-jou-tang","username":"ytang012","isRemote":null,"timestamp":"9/23/2020 21:32:18","email":"ytang012@gold.ac.uk","title":"Untitled","videoDocUrl":null,"interactiveUrl":null,"streamTwitch":null,"streamYouTube":null,"themes":["–"],"media":["Virtual Sculpture"],"numImages":1,"found":true,"events":[]}